[{"items": [{"tags": ["python", "tensorflow"], "owner": {"account_id": 438612, "reputation": 22264, "user_id": 826983, "user_type": "registered", "accept_rate": 69, "profile_image": "https://i.stack.imgur.com/B9PSD.jpg?s=256&g=1", "display_name": "Stefan Falk", "link": "https://stackoverflow.com/users/826983/stefan-falk"}, "is_answered": true, "view_count": 112064, "accepted_answer_id": 33922859, "answer_count": 5, "score": 111, "last_activity_date": 1559756240, "creation_date": 1448464138, "question_id": 33919948, "content_license": "CC BY-SA 3.0", "link": "https://stackoverflow.com/questions/33919948/how-to-set-adaptive-learning-rate-for-gradientdescentoptimizer", "title": "How to set adaptive learning rate for GradientDescentOptimizer?", "body": "<p>I am using TensorFlow to train a neural network. This is how I am initializing the <code>GradientDescentOptimizer</code>:</p>\n\n<pre><code>init = tf.initialize_all_variables()\nsess = tf.Session()\nsess.run(init)\n\nmse        = tf.reduce_mean(tf.square(out - out_))\ntrain_step = tf.train.GradientDescentOptimizer(0.3).minimize(mse)\n</code></pre>\n\n<p>The thing here is that I don't know how to set an update rule for the learning rate or a decay value for that. </p>\n\n<p>How can I use an adaptive learning rate here?</p>\n"}], "has_more": false, "quota_max": 300, "quota_remaining": 299}]