[{"items": [{"tags": ["tensorflow", "deep-learning"], "owner": {"user_type": "does_not_exist", "display_name": "user4911648"}, "is_answered": true, "view_count": 2893, "accepted_answer_id": 45714745, "answer_count": 2, "score": 1, "last_activity_date": 1502892823, "creation_date": 1496149811, "question_id": 44263228, "content_license": "CC BY-SA 3.0", "link": "https://stackoverflow.com/questions/44263228/when-do-i-have-to-explicitly-use-the-reuse-option-in-tensorflow", "title": "When do I have to explicitly use the reuse option in tensorflow", "body": "<p>in the Tensorflow Documentation it says, that everything within a <code>variable_scope</code> inherits the <code>reuse</code> option like this:</p>\n\n<pre><code>with tf.variable_scope(\"name\", reuse=True):\n    # inherits reuse=True\n</code></pre>\n\n<p>But my question is when I for example use one of these helper methods:</p>\n\n<pre><code>fc = tf.contrib.layers.fully_connected(input, 512, activation_fn=tf.nn.relu, weights_initializer=tf.contrib.layers.xavier_initializer(uniform=False))\n\nnorm = tf.contrib.layers.batch_norm(conv, 0.9, epsilon=1e-5, activation_fn=tf.nn.relu, scope=scope, fused=True)\n</code></pre>\n\n<p>Do I have to set the options: <code>reuse</code> and <code>scope</code> explicitly like this:</p>\n\n<pre><code>fc = tf.contrib.layers.fully_connected(input, 512, activation_fn=tf.nn.relu, weights_initializer=tf.contrib.layers.xavier_initializer(uniform=False), scope=scope, reuse=True)\n\nnorm = tf.contrib.layers.batch_norm(conv, 0.9, epsilon=1e-5, activation_fn=tf.nn.relu, scope=scope, reuse=True, is_training=self.is_training, fused=True)\n</code></pre>\n\n<p>or how does this work?</p>\n"}], "has_more": false, "quota_max": 300, "quota_remaining": 295}]