[{"items": [{"tags": ["python", "tensorflow"], "owner": {"user_type": "does_not_exist", "display_name": "user11170845"}, "is_answered": true, "view_count": 164, "accepted_answer_id": 55073180, "answer_count": 1, "score": 1, "last_activity_date": 1552095598, "creation_date": 1552053972, "last_edit_date": 1552054446, "question_id": 55064890, "content_license": "CC BY-SA 4.0", "link": "https://stackoverflow.com/questions/55064890/how-to-print-a-plain-text-constant-in-tensorflow-eager-execution-mode", "title": "How to print a plain text constant in tensorflow eager execution mode", "body": "<p>I have initialized a constant in tensorflow:</p>\n\n<pre><code>hello = tf.constant('hello')\n</code></pre>\n\n<p>In normal mode, <code>print(sess.run(hello).decode())</code> outputs the plain text in a constant Tensor.</p>\n\n<p>In eager execution mode however, the code above does not work.</p>\n\n<p>How can I print the plain text in constant Tensor hello?</p>\n\n<p>This question is NOT about <a href=\"https://stackoverflow.com/q/6269765/11074017\">python b'str'</a> or <a href=\"https://stackoverflow.com/q/40904979/11074017\">tf sess.run</a></p>\n"}], "has_more": false, "quota_max": 300, "quota_remaining": 104}]