[{"items": [{"tags": ["tensorflow", "keras", "tf.keras", "keras-2"], "owner": {"account_id": 26373, "reputation": 43816, "user_id": 68571, "user_type": "registered", "accept_rate": 79, "profile_image": "https://i.stack.imgur.com/Yw9Lg.png?s=256&g=1", "display_name": "VansFannel", "link": "https://stackoverflow.com/users/68571/vansfannel"}, "is_answered": true, "view_count": 798, "accepted_answer_id": 59643095, "answer_count": 2, "score": 0, "last_activity_date": 1658394395, "creation_date": 1578476052, "question_id": 59643009, "content_license": "CC BY-SA 4.0", "link": "https://stackoverflow.com/questions/59643009/migrate-convolutional2d-dim-ordering-parameter-to-conv2d-in-tf-keras", "title": "Migrate Convolutional2D dim_ordering parameter to Conv2D in tf.keras", "body": "<p>I'm newbie with Tensorflow and Keras, and I'm migrating the following code:</p>\n\n<pre><code>Convolution2D(64, 5, 5, activation='relu', border_mode='same', dim_ordering='tf', name='conv1_1')(inputs)\n</code></pre>\n\n<p>The interpreter suggest me this code:</p>\n\n<pre><code>Conv2D(64, (5, 5), activation=\"relu\", name=\"conv1_1\", padding=\"same\", data_format=\"channels_last\")\n</code></pre>\n\n<p>My question is:</p>\n\n<p>Is <code>dim_ordering='tf'</code> the same as <code>data_format=\"channels_last\"</code>?</p>\n"}], "has_more": false, "quota_max": 300, "quota_remaining": 18}]